{"$schema":"http://json-schema.org/draft-07/schema#","title":"PriceUpdated","required":["eventId","eventType","eventVersion","timestamp","correlationId","tenantId","source","payload","metadata"],"properties":{"eventType":{"const":"pricing.v1.price.updated"},"payload":{"type":"object","required":["priceId","productId","newPrice","updatedAt"],"properties":{"priceId":{"type":"string","format":"uuid"},"productId":{"type":"string","format":"uuid"},"sku":{"type":"string"},"oldPrice":{"type":"number"},"newPrice":{"type":"number","minimum":0},"channel":{"type":"string"},"reason":{"type":"string","enum":["cost_change","competition","promotion","seasonal","manual"]},"marginPercent":{"type":"number"},"cost":{"type":"number"},"updatedAt":{"type":"string","format":"date-time"},"updatedBy":{"type":"string"}}}}}